boldi/_plugins_version.py
boldi/plugins.py
boldi_plugins-0.9.7.dist-info/METADATA
boldi_plugins-0.9.7.dist-info/WHEEL
boldi_plugins-0.9.7.dist-info/RECORD
