Metadata-Version: 2.4
Name: boldi-plugins
Version: 0.9.7
Summary: boldi.plugins part of Boldi's Python libraries
Author-email: Boldizsár Palotás <boldizsar.palotas@gmail.com>
License: MIT
Requires-Python: >=3.10
